drf_easily_auth/__init__.py
drf_easily_auth/admin.py
drf_easily_auth/apps.py
drf_easily_auth/firebase/__init__.py
drf_easily_auth/firebase/auth.py
drf_easily_auth/firebase/utils.py
drf_easily_auth/management/__init__.py
drf_easily_auth/management/commands/__init__.py
drf_easily_auth/management/commands/syncfirebaseusers.py
drf_easily_auth/migrations/0001_initial.py
drf_easily_auth/migrations/__init__.py
drf_easily_auth/models.py
drf_easily_auth/tests.py
drf_easily_auth-0.2.0.dist-info/METADATA
drf_easily_auth-0.2.0.dist-info/WHEEL
drf_easily_auth-0.2.0.dist-info/RECORD
