Metadata-Version: 2.1
Name: drf-easily-auth
Version: 0.2.0
Summary: This package allows integration with Firebase for authentication outside the Django context.
Home-page: https://github.com/alexandre-meline/drf_easily_auth/
Keywords: Django,Firebase,Authentication,User Synchronization,DRF,Python,User Management,Security,API,JSON Web Tokens
Author: Alexandre Meline
Author-email: alexandre.meline.dev@gmail.com
Requires-Python: >=3.10,<4.0
Classifier: Programming Language :: Python :: 3
Classifier: Programming Language :: Python :: 3.10
Classifier: Programming Language :: Python :: 3.11
Classifier: Programming Language :: Python :: 3.12
Requires-Dist: django (>=5.0.4,<6.0.0)
Requires-Dist: djangorestframework (>=3.15.1,<4.0.0)
Requires-Dist: firebase-admin (>=6.5.0,<7.0.0)
